atsdpc/__init__.py
atsdpc/core.py
atsdpc/metrics.py
atsdpc/preprocessing.py
atsdpc/utils.py
kmdpc-0.1.2.dist-info/METADATA
kmdpc-0.1.2.dist-info/WHEEL
kmdpc-0.1.2.dist-info/top_level.txt
kmdpc-0.1.2.dist-info/RECORD
